MAIAI/__init__.py
MAIAI/agent.py
MAIAI/moderation.py
MAIAI/task.py
MAIAI-3.0.1.dist-info/LICENSE
MAIAI-3.0.1.dist-info/METADATA
MAIAI-3.0.1.dist-info/WHEEL
MAIAI-3.0.1.dist-info/top_level.txt
MAIAI-3.0.1.dist-info/RECORD
