Metadata-Version: 2.2
Name: MAIAI
Version: 3.0.1
Summary: A package to make working with AI simple.
Home-page: https://github.com/Mikemaii/MAIAI
Author: MikeMai
Author-email: mike.maiyoulian@gmail.com
Classifier: Programming Language :: Python :: 3
Classifier: License :: OSI Approved :: MIT License
Classifier: Operating System :: OS Independent
Requires-Python: >=3.10
License-File: LICENSE
Requires-Dist: openai
Dynamic: author
Dynamic: author-email
Dynamic: classifier
Dynamic: description
Dynamic: description-content-type
Dynamic: home-page
Dynamic: requires-dist
Dynamic: requires-python
Dynamic: summary
